rasesql_mcp_server/__init__.py
rasesql_mcp_server/server.py
rasesql_mcp_server/resources/db_resources.py
rasesql_mcp_server/tools/db_tool.py
rasesql_mcp_server/utils/__init__.py
rasesql_mcp_server/utils/db_config.py
rasesql_mcp_server/utils/db_operate.py
rasesql_mcp_server/utils/db_pool.py
rasesql_mcp_server/utils/logger_util.py
rasesql_mcp_server-1.0.3.dist-info/licenses/LICENSE
rasesql_mcp_server-1.0.3.dist-info/METADATA
rasesql_mcp_server-1.0.3.dist-info/WHEEL
rasesql_mcp_server-1.0.3.dist-info/entry_points.txt
rasesql_mcp_server-1.0.3.dist-info/top_level.txt
rasesql_mcp_server-1.0.3.dist-info/RECORD
