Metadata-Version: 2.4
Name: rasesql-mcp-server
Version: 1.0.3
Summary: A Model Context Protocol (MCP) server that enables secure interaction with RaseSQL、PostgreSQL databases.
Author-email: Frank Jin <j00131120@163.com>
Maintainer-email: Frank Jin <j00131120@163.com>
License-Expression: MIT
Project-URL: Homepage, https://gitee.com/frankjin/mcp-server
Project-URL: Documentation, https://gitee.com/frankjin/mcp-server/tree/master/rasesql_mcp_server/README.md
Project-URL: Repository, https://gitee.com/frankjin/mcp-server.git
Project-URL: Bug Tracker, https://gitee.com/frankjin/mcp-server/issues
Project-URL: Source Code, https://gitee.com/frankjin/mcp-server/tree/master/rasesql_mcp_server
Project-URL: Download, https://gitee.com/frankjin/mcp-server/tree/master/rasesql_mcp_server
Project-URL: Changelog, https://gitee.com/frankjin/mcp-server/tree/master/rasesql_mcp_server/CHANGELOG.md
Keywords: mcp,rasesql,postgresql,model-context-protocol,async,connection-pool
Classifier: Development Status :: 5 - Production/Stable
Classifier: Intended Audience :: Developers
Classifier: Intended Audience :: System Administrators
Classifier: Operating System :: OS Independent
Classifier: Programming Language :: Python :: 3
Classifier: Programming Language :: Python :: 3.12
Classifier: Programming Language :: Python :: 3.13
Classifier: Topic :: Database :: Front-Ends
Classifier: Topic :: Software Development :: Libraries :: Python Modules
Classifier: Topic :: System :: Networking
Classifier: Topic :: Database
Classifier: Framework :: AsyncIO
Classifier: Typing :: Typed
Requires-Python: >=3.12
License-File: LICENSE
Requires-Dist: fastmcp>=2.11.3
Requires-Dist: asyncpg>=0.30.0
Requires-Dist: mcp[cli]>=1.12.4
Requires-Dist: loguru>=0.7.3
Dynamic: license-file
